vitalai/__init__.py
vitalai-0.0.1.dist-info/LICENSE
vitalai-0.0.1.dist-info/METADATA
vitalai-0.0.1.dist-info/WHEEL
vitalai-0.0.1.dist-info/top_level.txt
vitalai-0.0.1.dist-info/RECORD
