Metadata-Version: 2.2
Name: vitalai
Version: 0.0.1
Summary: Vital.ai API Client
Home-page: https://github.com/vital-ai/vital-client-python
Author: Marc Hadfield
Author-email: marc@vital.ai
License: Apache License 2.0
Classifier: Programming Language :: Python :: 3.11
Classifier: License :: OSI Approved :: Apache Software License
Classifier: Operating System :: OS Independent
Requires-Python: >=3.11
License-File: LICENSE
Requires-Dist: vital-ai-vitalsigns
Requires-Dist: vital-ai-domain
Requires-Dist: vital-ai-aimp
Dynamic: author
Dynamic: author-email
Dynamic: classifier
Dynamic: description
Dynamic: description-content-type
Dynamic: home-page
Dynamic: license
Dynamic: requires-dist
Dynamic: requires-python
Dynamic: summary
